setup.py
qin_brick/__init__.py
qin_brick.egg-info/PKG-INFO
qin_brick.egg-info/SOURCES.txt
qin_brick.egg-info/dependency_links.txt
qin_brick.egg-info/requires.txt
qin_brick.egg-info/top_level.txt
qin_brick/authentication/__init__.py
qin_brick/authentication/block.py
qin_brick/authentication/role.py
qin_brick/authentication/role_permission.py
qin_brick/authentication/user.py
qin_brick/guard/__init__.py
qin_brick/guard/company.py
qin_brick/guard/company_product.py
qin_brick/guard/company_recharge_journal.py
qin_brick/guard/product.py