Metadata-Version: 1.0
Name: qin-brick
Version: 0.0.1
Summary: qin_brick, Qin bricks. db models for flask's application
Home-page: UNKNOWN
Author: UNKNOWN
Author-email: UNKNOWN
License: UNKNOWN
Platform: UNKNOWN
